xfp/__init__.py
xfp/py.typed
xfp/utils.py
xfp/xdict.py
xfp/xiter.py
xfp/xlist.py
xfp/functions/__init__.py
xfp/xresult/__init__.py
xfp/xresult/_xresult.py
xfp/xresult/xeither.py
xfp/xresult/xoption.py
xfp/xresult/xtry.py
xfp-1.1.0.dist-info/METADATA
xfp-1.1.0.dist-info/WHEEL
xfp-1.1.0.dist-info/RECORD
