Metadata-Version: 2.4
Name: xfp
Version: 1.1.0
Summary: functional programming library for python
Author: Sébastien VEY, Jérome LIERMANN
Requires-Python: ~=3.12.0
Requires-Dist: deprecation~=2.1.0
